MANIFEST.in
setup.py
humilis_secrets_vault/__init__.py
humilis_secrets_vault/meta.yaml.j2
humilis_secrets_vault/metadata.py
humilis_secrets_vault/outputs.yaml.j2
humilis_secrets_vault/resources.yaml.j2
humilis_secrets_vault.egg-info/PKG-INFO
humilis_secrets_vault.egg-info/SOURCES.txt
humilis_secrets_vault.egg-info/dependency_links.txt
humilis_secrets_vault.egg-info/entry_points.txt
humilis_secrets_vault.egg-info/not-zip-safe
humilis_secrets_vault.egg-info/requires.txt
humilis_secrets_vault.egg-info/top_level.txt