Metadata-Version: 1.1
Name: humilis-secrets-vault
Version: 0.2.2
Summary: Humilis layer that deploys a secrets vault
Home-page: http://github.com/humilis/humilis-secrets-vault
Author: German Gomez-Herrero
Author-email: german@findhotel.net
License: MIT
Platform: UNKNOWN
Classifier: Programming Language :: Python :: 3
